{
    "equipment": {
        "controller": {
            "intellicom": {
                "installed": 0,
                "friendlyName": ""
            },
            "intellitouch": {
                "installed": 0,
                "friendlyName": ""
            },
            "virtual": {
                "pumpController": "never",
                "chlorinatorController": "never"
            },
            "id": {
                "productName": "",
                "productNumber": "",
                "manufacturer": "",
                "description": ""
            }
        },
        "chlorinator": {
            "installed": 1,
            "desiredOutput": {
                "pool": 11,
                "spa": 2
            },
            "friendlyName": "",
            "id": {
                "productName": "Intellichlor--40",
                "productNumber": "",
                "manufacturer": "",
                "description": ""
            }
        },
        "pump": {
            "1": {
                "type": "VS",
                "externalProgram": {
                    "1": 1000,
                    "2": 1000,
                    "3": 2000,
                    "4": 1000
                },
                "friendlyName": ""
            },
            "2": {
                "type": "VS",
                "externalProgram": {
                    "1": 1000,
                    "2": 1000,
                    "3": 1000,
                    "4": 1000
                },
                "friendlyName": ""
            }
        },
        "intellichem": {
            "installed": 0
        },
        "spa": {
            "installed": 1
        },
        "solar": {
            "installed": 1
        },
        "circuit": {
            "friendlyName": {
                "1": "",
                "2": "",
                "3": "",
                "4": "",
                "5": "Waterfall Medium Low",
                "6": "",
                "7": "",
                "8": "",
                "9": "",
                "10": "",
                "11": "",
                "12": "Waterfall Low",
                "13": "Waterfall Medium",
                "14": "Waterfall High",
                "15": "Pool Low",
                "16": "",
                "17": "",
                "18": "",
                "19": "",
                "20": ""
            },
            "hideAux": false
        }
    },
    "poolController": {
        "appAddress": 33,
        "http": {
            "enabled": 1,
            "expressPort": 3000,
            "redirectToHttps": 0,
            "expressAuth": 0,
            "expressAuthFile": "/specs/assets/auth/users.htpasswd"
        },
        "https": {
            "enabled": 1,
            "expressPort": 3001,
            "expressAuth": 1,
            "expressAuthFile": "/specs/assets/auth/users.htpasswd",
            "expressKeyFile": "/specs/assets/data/server.key",
            "expressCertFile": "/specs/assets/data/server.crt"
        },
        "network": {
            "rs485Port": "/dev/tty.wchusbserial1420",
            "netConnect": 0,
            "netHost": "11.11.11.170",
            "netPort": 9801,
            "inactivityRetry": 100000
        },
        "notifications": {
            "version": {
                "remote": {
                    "version": "4.0.0",
                    "tag_name": "v4.0.0",
                    "dismissUntilNextRemoteVersionBump": false
                }
            }
        },
        "log": {
            "logLevel": "silly",
            "socketLogLevel": "info",
            "fileLog": {
                "enable": 0,
                "fileLogLevel": "silly",
                "fileName": "output.log"
            },
            "logPumpMessages": 1,
            "logDuplicateMessages": 0,
            "logConsoleNotDecoded": 1,
            "logConfigMessages": 0,
            "logMessageDecoding": 0,
            "logChlorinator": 0,
            "logIntellichem": 0,
            "logPacketWrites": 1,
            "logPumpTimers": 1,
            "logReload": 0,
            "logApi": 1
        },
        "database": {
            "influx": {
                "enabled": 0,
                "host": "localhost",
                "port": 8086,
                "database": "pool"
            }
        }
    },
    "integrations": {
        "socketISY": 0,
        "outputSocketToConsoleExample": 0,
        "outputToSmartThings": 0
    },
    "socketISY": {
        "username": "blank",
        "password": "blank",
        "ipaddr": "127.0.0.1",
        "port": 12345,
        "Variables": {
            "chlorinator": {
                "saltPPM": 16
            },
            "pump": {
                "1": {
                    "watts": 25,
                    "rpm": 24,
                    "currentprogram": 13,
                    "program1rpm": 10,
                    "program2rpm": 11,
                    "program3rpm": 12,
                    "program4rpm": 13,
                    "power": 14,
                    "timer": 15
                }
            }
        }
    },
    "outputSocketToConsoleExample": {
        "level": "warn"
    },
    "outputToSmartThings": {
        "address": "*",
        "port": "39500"
    },
    "version": "5.0.0",
    "meta": {
        "notifications": {
            "version": {
                "remote": {
                    "version": "4.0.0",
                    "tag_name": "v4.0.0",
                    "dismissUntilNextRemoteVersionBump": false
                }
            }
        }
    },
    "Hi I am an extra key": 0
}
