["blank", {
    "ID": 1,
    "CIRCUIT": "POOL",
    "friendlyName": "POOL",
    "CIRCUITNUM": 6,
    "MODE": "Schedule",
    "DURATION": "n/a",
    "START_TIME": "9:25",
    "END_TIME": "15:55",
    "DAYS": "Sunday Monday Tuesday Wednesday Thursday Friday Saturday "
}, {
    "ID": 2,
    "CIRCUIT": "WtrFall 2",
    "friendlyName": "WtrFall 2",
    "CIRCUITNUM": 13,
    "MODE": "Schedule",
    "DURATION": "n/a",
    "START_TIME": "14:57",
    "END_TIME": "15:8",
    "DAYS": "Sunday Tuesday Thursday Saturday "
}, {
    "ID": 3,
    "CIRCUIT": "CLEANER",
    "friendlyName": "CLEANER",
    "CIRCUITNUM": 4,
    "MODE": "Schedule",
    "DURATION": "n/a",
    "START_TIME": "10:15",
    "END_TIME": "11:0",
    "DAYS": "Sunday Monday Tuesday Wednesday Thursday Friday Saturday "
}, {
    "ID": 4,
    "CIRCUIT": "POOL",
    "friendlyName": "POOL",
    "CIRCUITNUM": 6,
    "MODE": "Egg Timer",
    "DURATION": "7:15"
}, {
    "ID": 5,
    "CIRCUIT": "CLEANER",
    "friendlyName": "CLEANER",
    "CIRCUITNUM": 4,
    "MODE": "Egg Timer",
    "DURATION": "4:0"
}, {
    "ID": 6,
    "CIRCUIT": "Pool Low2",
    "friendlyName": "Pool Low2",
    "CIRCUITNUM": 15,
    "MODE": "Schedule",
    "DURATION": "n/a",
    "START_TIME": "21:10",
    "END_TIME": "23:55",
    "DAYS": "Sunday Monday Tuesday Wednesday Thursday Friday Saturday "
}, {
    "ID": 7,
    "CIRCUIT": "Pool Low2",
    "friendlyName": "Pool Low2",
    "CIRCUITNUM": 15,
    "MODE": "Schedule",
    "DURATION": "n/a",
    "START_TIME": "0:5",
    "END_TIME": "9:20",
    "DAYS": "Sunday Monday Tuesday Wednesday Thursday Friday Saturday "
}, {
    "ID": 8,
    "CIRCUIT": "SPA LIGHT",
    "friendlyName": "SPA LIGHT",
    "CIRCUITNUM": 7,
    "MODE": "Egg Timer",
    "DURATION": "2:0"
}, {
    "ID": 9,
    "CIRCUIT": "JETS",
    "friendlyName": "JETS",
    "CIRCUITNUM": 2,
    "MODE": "Egg Timer",
    "DURATION": "3:45"
}, {
    "ID": 10,
    "CIRCUIT": "PATH LIGHTS",
    "friendlyName": "PATH LIGHTS",
    "CIRCUITNUM": 9,
    "MODE": "Egg Timer",
    "DURATION": "4:15"
}, {
    "ID": 11,
    "CIRCUIT": "SPILLWAY",
    "friendlyName": "SPILLWAY",
    "CIRCUITNUM": 11,
    "MODE": "Schedule",
    "DURATION": "n/a",
    "START_TIME": "13:0",
    "END_TIME": "13:11",
    "DAYS": "Sunday Monday Tuesday Wednesday Thursday Friday Saturday "
}, {
    "ID": 12,
    "CIRCUIT": "WtrFall 1.5",
    "friendlyName": "WtrFall 1.5",
    "CIRCUITNUM": 5,
    "MODE": "Schedule",
    "DURATION": "n/a",
    "START_TIME": "13:20",
    "END_TIME": "13:40",
    "DAYS": "Sunday Tuesday Thursday "
}]
